LICENSE.txt
MANIFEST.in
README.rst
setup.py
data/harvard500-cc.graph
data/harvard500-cc.properties
data/harvard500.graph
data/harvard500.offsets
data/harvard500.properties
data/wb-cs.stanford.graph
data/wb-cs.stanford.properties
include/bitfile.h
include/bvgraph.h
include/bvgraphfun.h
include/gamma.h
include/pstdint.h
include/uthash.h
include/zeta.h
pylibbvg.egg-info/PKG-INFO
pylibbvg.egg-info/SOURCES.txt
pylibbvg.egg-info/dependency_links.txt
pylibbvg.egg-info/eager_resources.txt
pylibbvg.egg-info/requires.txt
pylibbvg.egg-info/top_level.txt
src/bitfile.c
src/bvg.c
src/bvg.pyx
src/bvgraph.c
src/bvgraph_inline_io.h
src/bvgraph_internal.h
src/bvgraph_iterator.c
src/bvgraph_random.c
src/clibbvg.pxd
src/properties.c
src/util.c
test/test_head_tail_1000_64bit.py
test/test_networkx.py
test/testinterface.py
test/testlibbvg.py
test/testunittest.py