Metadata-Version: 1.1
Name: pylibbvg
Version: 2.0.25
Summary: A python interface for decompressing Boldi-Vigna graphs
Home-page: https://github.com/dgleich/libbvg
Author: David F. Gleich, Wei-Yen Day and Yongyang Yu
Author-email: dgleich@purdue.edu, yu163@purdue.edu
License: UNKNOWN
Keywords: python interface for decompressing bvgraph
Platform: UNKNOWN
Classifier: Development Status :: 4 - Beta
Classifier: Intended Audience :: Developers
Classifier: Programming Language :: Python
Classifier: Programming Language :: Python :: 2
Classifier: Programming Language :: Python :: 2.6
Classifier: Programming Language :: Python :: 2.7
Classifier: Programming Language :: Python :: 3
Classifier: Programming Language :: Python :: 3.1
Classifier: Programming Language :: Python :: 3.2
Classifier: Programming Language :: Python :: 3.3
Classifier: Programming Language :: Cython
